trytond/modules/cashbook_investment/README.rst
trytond/modules/cashbook_investment/__init__.py
trytond/modules/cashbook_investment/asset.py
trytond/modules/cashbook_investment/assetsetting.py
trytond/modules/cashbook_investment/assetsetting.xml
trytond/modules/cashbook_investment/book.py
trytond/modules/cashbook_investment/book.xml
trytond/modules/cashbook_investment/line.py
trytond/modules/cashbook_investment/line.xml
trytond/modules/cashbook_investment/menu.xml
trytond/modules/cashbook_investment/message.xml
trytond/modules/cashbook_investment/mixin.py
trytond/modules/cashbook_investment/reconciliation.py
trytond/modules/cashbook_investment/reconciliation.xml
trytond/modules/cashbook_investment/splitline.py
trytond/modules/cashbook_investment/splitline.xml
trytond/modules/cashbook_investment/tryton.cfg
trytond/modules/cashbook_investment/types.py
trytond/modules/cashbook_investment/valuestore.py
trytond/modules/cashbook_investment/versiondep.txt
trytond/modules/cashbook_investment/docs/settings.txt
trytond/modules/cashbook_investment/locale/de.po
trytond/modules/cashbook_investment/locale/en.po
trytond/modules/cashbook_investment/tests/__init__.py
trytond/modules/cashbook_investment/tests/book.py
trytond/modules/cashbook_investment/tests/reconciliation.py
trytond/modules/cashbook_investment/tests/test_module.py
trytond/modules/cashbook_investment/tests/valuestore.py
trytond/modules/cashbook_investment/tests/yieldtest.py
trytond/modules/cashbook_investment/view/assetconf_form.xml
trytond/modules/cashbook_investment/view/book_form.xml
trytond/modules/cashbook_investment/view/book_list.xml
trytond/modules/cashbook_investment/view/book_tree.xml
trytond/modules/cashbook_investment/view/line_form.xml
trytond/modules/cashbook_investment/view/line_list.xml
trytond/modules/cashbook_investment/view/line_recon_list.xml
trytond/modules/cashbook_investment/view/recon_form.xml
trytond/modules/cashbook_investment/view/recon_list.xml
mds_cashbook_investment-7.0.14.dist-info/LICENSE
mds_cashbook_investment-7.0.14.dist-info/METADATA
mds_cashbook_investment-7.0.14.dist-info/WHEEL
mds_cashbook_investment-7.0.14.dist-info/entry_points.txt
mds_cashbook_investment-7.0.14.dist-info/top_level.txt
mds_cashbook_investment-7.0.14.dist-info/RECORD
